resource_api
