Metadata-Version: 1.0
Name: resource-api
Version: 3.1.1
Summary: A framework that allows developers declaratively define resources and relationships between them
Home-page: http://resource-api.readthedocs.org/
Author: F-Secure Corporation
Author-email: <TBD>
License: UNKNOWN
Platform: UNKNOWN
